part_builder/__init__.py
part_builder/part_builder.py
part_builder/part_exception.py
synth_part_builder/__init__.py
synth_part_builder/part_builder.py
synth_part_builder/part_exception.py
synth_part_builder-1.1.dist-info/METADATA
synth_part_builder-1.1.dist-info/WHEEL
synth_part_builder-1.1.dist-info/top_level.txt
synth_part_builder-1.1.dist-info/RECORD
